_examples/__init__.py
examples/__init__.py
gharchive/__init__.py
gharchive/exc.py
gharchive/logger.py
gharchive/main.py
gharchive/models.py
gharchive/search.py
gharchive/unzip.py
tests/__init__.py
tests/base.py
tests/config.py
tests/test_decompress.py
tests/test_models.py
tests/test_search_date.py
tests/utils/__init__.py
tests/utils/imports.py
gharchive-0.2.2.dist-info/LICENSE.md
gharchive-0.2.2.dist-info/METADATA
gharchive-0.2.2.dist-info/WHEEL
gharchive-0.2.2.dist-info/entry_points.txt
gharchive-0.2.2.dist-info/top_level.txt
gharchive-0.2.2.dist-info/RECORD
