Metadata-Version: 2.1
Name: gharchive
Version: 0.2.2
Summary: Python SDK to access Github Archive
Home-page: https://github.com/nickderobertis/py-gh-archive
Author: Nick DeRobertis
Author-email: whoopnip@gmail.com
License: MIT
Project-URL: Code, https://github.com/nickderobertis/py-gh-archive
Project-URL: Documentation, https://nickderobertis.github.io/py-gh-archive
Platform: UNKNOWN
Classifier: Development Status :: 3 - Alpha
Classifier: Intended Audience :: Developers
Classifier: Programming Language :: Python :: 3.6
Classifier: Programming Language :: Python :: 3.7
Requires-Dist: pandas
Requires-Dist: python-dateutil
Requires-Dist: requests
Provides-Extra: mgzip
Requires-Dist: mgzip ; extra == 'mgzip'
